{
  "name": "Brian Morrison’s Mobile Mechanics",
  "street": "",
  "city": "Pensacola",
  "country": "United States",
  "country_code": "US",
  "url": "https://www.facebook.com/BriansMobileMechanics/",
  "facebook": "https://www.facebook.com/BriansMobileMechanics/",
  "phone_number": "(850) 982-6134",
  "review_score": 4.8,
  "google_maps_url": "https://maps.google.com/?cid=16510841622887274934&g_mp=Cidnb29nbGUubWFwcy5wbGFjZXMudjEuUGxhY2VzLlNlYXJjaFRleHQQAhgEIAA",
  "google_first_url": "https://www.manta.com/c/mkk70kj/brian-morrison-s-mobile-mechanics",
  "business_category": "auto_repair",
  "published": "2026-06-10T12:10:31.463Z",
  "emails": "briansmobilemechanics@gmail.com"
}
