{
  "id": "1780801422580",
  "type": "search",
  "label": "Discover В· 1 searches",
  "batchNum": "1780802245178",
  "running": false,
  "startedAt": "2026-06-07T03:03:42.580Z",
  "finishedAt": "2026-06-07T03:20:27.732Z",
  "exitCode": 0,
  "currentStage": "live",
  "stages": {
    "discover": "done",
    "verify": "done",
    "import": "done",
    "facebook": "done",
    "design": "done",
    "finalize": "done",
    "live": "done"
  },
  "log": "\nв•җв•җв•җв•җв•җв•җв•җв•җв•җв•җв•җв•җв•җв•җв•җв•җв•җв•җв•җв•җв•җв•җв•җв•җв•җв•җв•җв•җв•җв•җв•җв•җв•җв•җв•җв•җв•җв•җв•җв•җв•җв•җв•җв•җв•җв•җв•җв•җв•җв•җв•җв•җв•җв•җв•җв•җв•җв•җв•җв•җ\n  1/4 вҖ” Discover (Google Places + SERP)\nв•җв•җв•җв•җв•җв•җв•җв•җв•җв•җв•җв•җв•җв•җв•җв•җв•җв•җв•җв•җв•җв•җв•җв•җв•җв•җв•җв•җв•җв•җв•җв•җв•җв•җв•җв•җв•җв•җв•җв•җв•җв•җв•җв•җв•җв•җв•җв•җв•җв•җв•җв•җв•җв•җв•җв•җв•җв•җв•җв•җ\n\n\nLead discovery вҖ” LIVE\n  Grid: 29250 searches (375 cities Г— 78 categories)\n  Order: shuffled (random each run)\n  Caps: 1 Google searches, $1 SERP budget, batch SERP (wait 5 min)\n\n  вҶ’ mobile car wash in Gastonia NC\n  в—Ӣ Google search cap reached (1)\n\n  SERP batch: 8 website survivor(s) (DataForSEO Standard, normal priority)вҖҰ\n\n  Submitted 8 SERP task(s) in batch\n  Waiting 5 min before checking tasks_readyвҖҰ\n  вҖҰ 6 SERP task(s) still queued (5 min elapsed, polling again)\n  вҖҰ 2 SERP task(s) still queued (6 min elapsed, polling again)\n  вҖҰ 1 SERP task(s) still queued (7 min elapsed, polling again)\n  вҖҰ 1 SERP task(s) still queued (8 min elapsed, polling again)\n  вҖҰ 1 SERP task(s) still queued (9 min elapsed, polling again)\n    вҖҰ SERP \"Carolina Details LLC Mobile Detailing Business\" skip (no_matching_facebook_in_serp)\n    вҖҰ SERP \"J&C mobile detailing\" вң“ Gastonia (matched_fb_rank_1)\n    вҖҰ SERP \"Ramirez mobile detailing\" вң“ Gastonia (matched_fb_rank_4)\n    вҖҰ SERP \"Z&D Mobile Detailing,LLC\" вң“ Gastonia (matched_fb_rank_1)\n    вҖҰ SERP \"Carolinas Mobile Detailing Company\" вң“ Gastonia (matched_fb_rank_2)\n    вҖҰ SERP \"Dhop Mobile Detailing\" вң“ Gastonia (matched_fb_rank_3)\n    вҖҰ SERP \"JвҖҷs mobile detailing\" вң“ Gastonia (matched_fb_rank_2)\n    вҖҰ SERP \"Fresh Finish Mobile Detail\" вң“ Gastonia (matched_fb_rank_1)\n\n  Wrote 7 candidates вҶ’ data\\discover\\output\\candidates-2026-06-07T03-14-07.json\n  Website filter вҶ’ data\\discover\\output\\website-filter-2026-06-07T03-14-07.json\n\n  Stats вҶ’ data\\discover\\output\\run-2026-06-07T03-14-07.json\n  Raw: 20 | New: 20 | Website survivors: 8\n  SERP checked: 8 | Batch submitted: 8 | Final: 7\n  Spend: $0.0048 SERP | 1 Google searches\n\n\nв•җв•җв•җв•җв•җв•җв•җв•җв•җв•җв•җв•җв•җв•җв•җв•җв•җв•җв•җв•җв•җв•җв•җв•җв•җв•җв•җв•җв•җв•җв•җв•җв•җв•җв•җв•җв•җв•җв•җв•җв•җв•җв•җв•җв•җв•җв•җв•җв•җв•җв•җв•җв•җв•җв•җв•җв•җв•җв•җв•җ\n  2/4 вҖ” Verify Facebook + export import JSON\nв•җв•җв•җв•җв•җв•җв•җв•җв•җв•җв•җв•җв•җв•җв•җв•җв•җв•җв•җв•җв•җв•җв•җв•җв•җв•җв•җв•җв•җв•җв•җв•җв•җв•җв•җв•җв•җв•җв•җв•җв•җв•җв•җв•җв•җв•җв•җв•җв•җв•җв•җв•җв•җв•җв•җв•җв•җв•җв•җв•җ\n\n\nDiscover verify-export вҖ” 7 candidate(s)\n  Activity filter: posts within 12 months (use --skip-activity to disable)\n\n  вҶ’ J&C mobile detailingвҖҰ\n    в—Ӣ SKIP вҖ” fb_website_owned_domain (https://www.jjmobiledetailing17.com/)\n  вҶ’ Ramirez mobile detailingвҖҰ\n    в—Ӣ SKIP вҖ” no email on Facebook profile\n  вҶ’ Z&D Mobile Detailing,LLCвҖҰ\n    вң“ PASS вҖ” Zdmobiledetailing@gmail.com вҖ” stale site https://zdmobiledetailing-cardetailingservice.business.site/?utm_source=gmb\n  вҶ’ Carolinas Mobile Detailing CompanyвҖҰ\n    в—Ӣ SKIP вҖ” fb_website_owned_domain (https://www.jjmobiledetailing17.com/)\n  вҶ’ Dhop Mobile DetailingвҖҰ\n    в—Ӣ SKIP вҖ” no email on Facebook profile\n  вҶ’ JвҖҷs mobile detailingвҖҰ\n    в—Ӣ SKIP вҖ” fb_website_owned_domain (http://www.jsmobiledetailing.com/)\n  вҶ’ Fresh Finish Mobile DetailвҖҰ\n    вң“ PASS вҖ” freshfinishwash25@gmail.com\n\n  Verified: 2 | Skipped: 5 | Failed: 0\n  Import-ready вҶ’ data\\discover\\output\\verified-2026-06-07T03-17-25.json\n  Report вҶ’ data\\discover\\output\\verify-report-2026-06-07T03-17-25.json\n\n\nв•җв•җв•җв•җв•җв•җв•җв•җв•җв•җв•җв•җв•җв•җв•җв•җв•җв•җв•җв•җв•җв•җв•җв•җв•җв•җв•җв•җв•җв•җв•җв•җв•җв•җв•җв•җв•җв•җв•җв•җв•җв•җв•җв•җв•җв•җв•җв•җв•җв•җв•җв•җв•җв•җв•җв•җв•җв•җв•җв•җ\n  3/4 вҖ” Import leads\nв•җв•җв•җв•җв•җв•җв•җв•җв•җв•җв•җв•җв•җв•җв•җв•җв•җв•җв•җв•җв•җв•җв•җв•җв•җв•җв•җв•җв•җв•җв•җв•җв•җв•җв•җв•җв•җв•җв•җв•җв•җв•җв•җв•җв•җв•җв•җв•җв•җв•җв•җв•җв•җв•җв•җв•җв•җв•җв•җв•җ\n\nImported 2 lead(s) вҶ’ batch-1780802245178\n  z-d-mobile-detailing-llc-gastonia\n  fresh-finish-mobile-detail-gastonia\n\nSlugs file: data/batches/batch-1780802245178/slugs.txt\nNext: npm run pipeline:run -- data/batches/batch-1780802245178/slugs.txt\n\nв•җв•җв•җв•җв•җв•җв•җв•җв•җв•җв•җв•җв•җв•җв•җв•җв•җв•җв•җв•җв•җв•җв•җв•җв•җв•җв•җв•җв•җв•җв•җв•җв•җв•җв•җв•җв•җв•җв•җв•җв•җв•җв•җв•җв•җв•җв•җв•җв•җв•җв•җв•җв•җв•җв•җв•җв•җв•җв•җв•җ\n  4/4 вҖ” Main pipeline (verify вҶ’ stitch вҶ’ post-build вҶ’ outreach queue)\nв•җв•җв•җв•җв•җв•җв•җв•җв•җв•җв•җв•җв•җв•җв•җв•җв•җв•җв•җв•җв•җв•җв•җв•җв•җв•җв•җв•җв•җв•җв•җв•җв•җв•җв•җв•җв•җв•җв•җв•җв•җв•җв•җв•җв•җв•җв•җв•җв•җв•җв•җв•җв•җв•җв•җв•җв•җв•җв•җв•җ\n\n\nFacebook Leads pipeline вҖ” batch 1780802245178 (2 slug(s))\n\n\nв•җв•җ z-d-mobile-detailing-llc-gastonia в•җв•җ\n  verifying Facebook profileвҖҰ\n  вң“ PASS вҖ” fb_website_owned_but_dead\n  enriching briefвҖҰ\n  вң“ brief.md + prompt-input.json\n  вң“ stitch prompt\n\nв•җв•җ fresh-finish-mobile-detail-gastonia в•җв•җ\n  verifying Facebook profileвҖҰ\n  вң“ PASS вҖ” fb_website_field_empty\n  enriching briefвҖҰ\n  вң“ brief.md + prompt-input.json\n  вң“ stitch prompt\n\nStitch pool: 2 concurrent worker(s), 6 API key(s), 2 slug(s). Credit failover enabled.\nRecording Facebook source metadataвҖҰ\nRecording Facebook source metadataвҖҰ\nStitch will choose colors and typography from business identity.\nWrote C:\\Users\\Damian\\Documents\\Facebook Leads\\f\\preview\\fresh-finish-mobile-detail-gastonia\\stitch\\prompt.md\n\nв”Җв”Җ fresh-finish-mobile-detail-gastonia в”Җв”Җ\nStitch project: Outreach вҖ” fresh-finish-mobile-detail-gastonia\nStitch will choose colors and typography from business identity.\nWrote C:\\Users\\Damian\\Documents\\Facebook Leads\\f\\preview\\z-d-mobile-detailing-llc-gastonia\\stitch\\prompt.md\n\nв”Җв”Җ z-d-mobile-detailing-llc-gastonia в”Җв”Җ\nStitch project: Outreach вҖ” z-d-mobile-detailing-llc-gastonia\n\nAttempt A: full prompt.md + HTML directive (single try)вҖҰ\n  вҶ’ generate_screen_from_text (single-attempt-full)вҖҰ\n\nAttempt A: full prompt.md + HTML directive (single try)вҖҰ\n  вҶ’ generate_screen_from_text (single-attempt-full)вҖҰ\nSaved design system: C:\\Users\\Damian\\Documents\\Facebook Leads\\f\\preview\\fresh-finish-mobile-detail-gastonia\\stitch\\DESIGN.md\nAttempt A included htmlCode вҖ” skipping phase 2.\n\nPulling full Stitch export (HTML, CSS, screenshots, tokens, вҖҰ)вҖҰ\n  вҶ“ htmlcode.html (htmlCode)\n  вҶ“ screenshot.png (screenshot)\nPrimary HTML: C:\\Users\\Damian\\Documents\\Facebook Leads\\f\\preview\\fresh-finish-mobile-detail-gastonia\\stitch\\design.html\n\nSite ready: C:\\Users\\Damian\\Documents\\Facebook Leads\\f\\preview\\fresh-finish-mobile-detail-gastonia/index.html\nRaw export: C:\\Users\\Damian\\Documents\\Facebook Leads\\f\\preview\\fresh-finish-mobile-detail-gastonia\\stitch\\export/ (4 files)\nGoogle Map embed added for: Gastonia, Gastonia, United States\n\nRunning design skills (emil вҶ’ taste вҶ’ audit вҶ’ harden вҶ’ polish)вҖҰ\n  вң“ normalize: single DOCTYPE\n  вң“ emil: replaced transition: all\n  вң“ emil: added :active press feedback\n  вң“ craft: injected brief fonts (Source Serif 4 / Nunito)\n  вң“ harden: preview-only form behavior (removed fake send UX)\n  вң“ harden: mobile nav aria labels\nDesign QA report: fresh-finish-mobile-detail-gastonia/design-qa/report.md (review blockers)\n\nRunning site evaluation (broken links, images, structure)вҖҰ\n  вң— Stitch AI placeholder images still present вҖ” run images:apply\nSite eval report: fresh-finish-mobile-detail-gastonia/design-qa/site-eval.md\n\nв”Җв”Җ post-build: fresh-finish-mobile-detail-gastonia в”Җв”Җ\n  вң“ map:inject (placeholder, brief)\n  вң“ mockup-notice вҖ” css: mockup notice styles\n  вң“ content-fix вҖ” added button sizing safety CSS\n  вң“ qa-autofix вҖ” inserted fallback #credibility section\n  вң“ images:apply\n  вҶ» design QA + site eval + responsive + mobile layoutвҖҰ\n  вң“ mobile-layout:autofix вҖ” refreshed map layout CSS; injected mobile safety CSS; bumped 10px label text; pulled in decorative absolute offsets; body overflow-x-clip; section overflow-hidden for decorative layers; responsive horizontal margins (9 blocks)\n  в—Ӣ responsive-qa: mobile: body text below 12px\n  вң“ qa:check\n  вң“ git commit вҖ” preview/fresh-finish-mobile-detail-gastonia, index.html, .github/workflows/pages.yml\n  вң“ git push вҶ’ main\n  вҖҰ waiting for GitHub Pages (https://sites.damianbasilio.dev/preview/fresh-finish-mobile-detail-gastonia)вҖҰ\nSaved design system: C:\\Users\\Damian\\Documents\\Facebook Leads\\f\\preview\\z-d-mobile-detailing-llc-gastonia\\stitch\\DESIGN.md\nAttempt A included htmlCode вҖ” skipping phase 2.\n\nPulling full Stitch export (HTML, CSS, screenshots, tokens, вҖҰ)вҖҰ\n  вҶ“ htmlcode.svg (htmlCode)\n  вҶ“ screenshot.png (screenshot)\n  вң“ live mockup (21s)\n  вң“ enqueued for review fresh-finish-mobile-detail-gastonia\n\nв”Җв”Җ Batch 1780802245178 complete в”Җв”Җ\n  Passed: 1 | Skipped: 0 | Failed: 1\n  Status: data/batches/batch-1780802245178/status.json\n  Review: data/batches/batch-1780802245178/queues.json\n\nвҶ’ Open http://localhost:3456 to review and approve emails one at a time.\n\nвң“ Complete вҖ” batch 1780802245178, 2 slug(s)\n  Review: npm run server вҶ’ http://localhost:3456\n  Batch: data/batches/batch-1780802245178/\n\n"
}
