{
  "name": "Overall Mobile Mechanic",
  "street": "Pensacola",
  "city": "Pensacola",
  "country": "FL 32502",
  "country_code": "US",
  "url": "https://www.facebook.com/Jaysmobilemechanis/",
  "facebook": "https://www.facebook.com/Jaysmobilemechanis/",
  "phone_number": "265.663 7265",
  "review_score": 1,
  "google_maps_url": "https://maps.google.com/?cid=5641720134809544666&g_mp=Cidnb29nbGUubWFwcy5wbGFjZXMudjEuUGxhY2VzLlNlYXJjaFRleHQQAhgEIAA",
  "google_first_url": "https://www.yelp.com/search?find_desc=Mobile+Mechanic&find_loc=Pensacola%2C+FL",
  "business_category": "auto_repair",
  "published": "2026-06-10T12:10:38.181Z",
  "emails": "lewisautomotive85@gmail.com"
}
