{
  "name": "Christina Joy Photography",
  "street": "317 South Central Street",
  "city": "Visalia",
  "country": "CA 93291",
  "country_code": "US",
  "url": "https://www.facebook.com/cjhopperphotography/",
  "facebook": "https://www.facebook.com/cjhopperphotography/",
  "phone_number": "(559) 402-0024",
  "review_score": 5,
  "google_maps_url": "https://maps.google.com/?cid=2014205632363986786&g_mp=Cidnb29nbGUubWFwcy5wbGFjZXMudjEuUGxhY2VzLlNlYXJjaFRleHQQAhgEIAA",
  "google_first_url": "https://www.instagram.com/cjhopper/",
  "business_category": "photographer",
  "published": "2026-06-07T20:20:09.293Z",
  "emails": "christina@cjhopper.com",
  "sentAt": "2026-06-07T20:42:27.433Z"
}
