{
  "startedAt": "2026-06-06T22:55:30.860Z",
  "dryRun": false,
  "gridSize": 29250,
  "rawPlaces": 20,
  "newPlaces": 20,
  "skippedKnownPlace": 0,
  "websiteSurvivors": 1,
  "websiteRejected": 19,
  "serpChecked": 1,
  "serpSkippedBudget": 0,
  "gbpFacebookDirect": 0,
  "serpRejected": 0,
  "serpErrors": 0,
  "skippedExistingFb": 0,
  "finalCandidates": 1,
  "shuffled": true,
  "finishedAt": "2026-06-06T22:56:44.440Z",
  "budget": {
    "maxGoogleSearches": 1,
    "googleSearchesUsed": 1,
    "serpBudgetUsd": 0.05,
    "serpChecksUsed": 1,
    "serpSpendUsd": 0.0006
  }
}
